apollo_py_numpy_core/__init__.py
apollo_py_numpy_core/spatial/__init__.py
apollo_py_numpy_core/spatial/isometries.py
apollo_py_numpy_core/spatial/lie/__init__.py
apollo_py_numpy_core/spatial/lie/h1.py
apollo_py_numpy_core/spatial/lie/se3_implicit.py
apollo_py_numpy_core/spatial/lie/se3_implicit_quaternion.py
apollo_py_numpy_core/spatial/lie/so3.py
apollo_py_numpy_core/spatial/matrices.py
apollo_py_numpy_core/spatial/quaternions.py
apollo_py_numpy_core/spatial/rotation_matrices.py
apollo_py_numpy_core/spatial/vectors.py
apollo_py_numpy_core-0.0.1.dist-info/LICENSE
apollo_py_numpy_core-0.0.1.dist-info/METADATA
apollo_py_numpy_core-0.0.1.dist-info/WHEEL
apollo_py_numpy_core-0.0.1.dist-info/RECORD
